threedigrid_builder/application.py
threedigrid_builder/cli.py
threedigrid_builder/constants.py
threedigrid_builder/exceptions.py
threedigrid_builder/__init__.py
threedigrid_builder/base/array.py
threedigrid_builder/base/interfaces.py
threedigrid_builder/base/lines.py
threedigrid_builder/base/linestrings.py
threedigrid_builder/base/line_halfs.py
threedigrid_builder/base/nodes.py
threedigrid_builder/base/pumps.py
threedigrid_builder/base/quarters.py
threedigrid_builder/base/settings.py
threedigrid_builder/base/surfaces.py
threedigrid_builder/base/__init__.py
threedigrid_builder/grid/boundary_conditions.py
threedigrid_builder/grid/channels.py
threedigrid_builder/grid/connection_nodes.py
threedigrid_builder/grid/cross_section_definitions.py
threedigrid_builder/grid/cross_section_locations.py
threedigrid_builder/grid/dem_average_area.py
threedigrid_builder/grid/embedded.py
threedigrid_builder/grid/exchange_lines.py
threedigrid_builder/grid/grid.py
threedigrid_builder/grid/grid_refinement.py
threedigrid_builder/grid/groundwater.py
threedigrid_builder/grid/initial_waterlevels.py
threedigrid_builder/grid/linear.py
threedigrid_builder/grid/lines_1d2d.py
threedigrid_builder/grid/obstacles.py
threedigrid_builder/grid/pipes.py
threedigrid_builder/grid/potential_breaches.py
threedigrid_builder/grid/quadtree.py
threedigrid_builder/grid/structures.py
threedigrid_builder/grid/windshielding.py
threedigrid_builder/grid/zero_d.py
threedigrid_builder/grid/__init__.py
threedigrid_builder/grid/fgrid/_fgrid.cp39-win_amd64.pyd
threedigrid_builder/grid/fgrid/__init__.py
threedigrid_builder/interface/db.py
threedigrid_builder/interface/dict_out.py
threedigrid_builder/interface/geopackage.py
threedigrid_builder/interface/gridadmin.py
threedigrid_builder/interface/raster_gdal.py
threedigrid_builder/interface/__init__.py
threedigrid_builder/tests/conftest.py
threedigrid_builder/tests/test_array.py
threedigrid_builder/tests/test_boundary_conditions.py
threedigrid_builder/tests/test_channels.py
threedigrid_builder-1.24.8.dist-info/DELVEWHEEL
threedigrid_builder-1.24.8.dist-info/entry_points.txt
threedigrid_builder-1.24.8.dist-info/METADATA
threedigrid_builder-1.24.8.dist-info/RECORD
threedigrid_builder-1.24.8.dist-info/WHEEL
threedigrid_builder-1.24.8.dist-info/licenses/LICENSE
