Metadata-Version: 2.2
Name: threedigrid-builder
Version: 1.24.8
Summary: Generate a 3Di simulation grid from a model schematisation
Author-Email: Martijn Siemerink <martijn.siemerink@nelen-schuurmans.nl>
License: GNU General Public License v3.0
Classifier: Programming Language :: Python :: 3
Classifier: Intended Audience :: Science/Research
Classifier: Intended Audience :: Developers
Classifier: Development Status :: 5 - Production/Stable
Classifier: Topic :: Scientific/Engineering
Classifier: Topic :: Software Development
Classifier: Operating System :: Unix
Classifier: Operating System :: MacOS
Classifier: Operating System :: Microsoft :: Windows
Classifier: License :: Other/Proprietary License
Project-URL: Documentation, https://docs.3di.lizard.net/
Project-URL: Repository, https://github.com/nens/threedigrid-builder
Requires-Python: >=3.9
Requires-Dist: numpy<3.0,>=1.15
Requires-Dist: threedi-schema==0.300.*
Requires-Dist: shapely>=2
Requires-Dist: pyproj>=3
Requires-Dist: condenser[geo]>=0.1.1
Requires-Dist: sqlalchemy>=1.4.1
Provides-Extra: test
Requires-Dist: pytest; extra == "test"
Requires-Dist: pytest-cov; extra == "test"
Provides-Extra: gridadmin
Requires-Dist: h5py>=2.7; extra == "gridadmin"
Provides-Extra: gpkg
Requires-Dist: geopandas; extra == "gpkg"
Provides-Extra: cli
Requires-Dist: typer; extra == "cli"
